[
    {
        "target": "#total",
        "placement": "left",
        "content": "xxx",
        "left": 5,
        "bottom": 0,
        "tour_bottom": 0
    },
    {
        "target": "#relation-graph",
        "placement": "left",
        "content": "xxx",
        "left": 5,
        "bottom": 0,
        "tour_bottom": 0
    },
    {
        "target": "#sankey",
        "placement": "left",
        "content": "xxx",
        "left": 5,
        "bottom": 0,
        "tour_bottom": 0
    },
    {
        "target": "#region-bar",
        "placement": "left",
        "content": "xxx",
        "left": 75,
        "bottom": 0,
        "tour_bottom": 30
    }
]